common_osint_model/__init__.py
common_osint_model/utils.py
common_osint_model/models/__init__.py
common_osint_model/models/autonomous_system.py
common_osint_model/models/dns.py
common_osint_model/models/domain.py
common_osint_model/models/host.py
common_osint_model/models/http.py
common_osint_model/models/service.py
common_osint_model/models/ssh.py
common_osint_model/models/tls.py
common_osint_model-0.6.2.dist-info/METADATA
common_osint_model-0.6.2.dist-info/WHEEL
common_osint_model-0.6.2.dist-info/entry_points.txt
common_osint_model-0.6.2.dist-info/licenses/LICENSE
common_osint_model-0.6.2.dist-info/RECORD
