Metadata-Version: 2.4
Name: common-osint-model
Version: 0.6.2
Summary: Converting data from services like BinaryEdge, Censys and Shodan to a common data model.
Project-URL: Homepage, https://github.com/3c7/common-osint-model
Project-URL: Repository, https://github.com/3c7/common-osint-model
Author-email: 3c7 <3c7@posteo.de>
License-Expression: MIT
License-File: LICENSE
Classifier: License :: OSI Approved :: MIT License
Classifier: Operating System :: OS Independent
Classifier: Programming Language :: Python :: 3
Requires-Python: <4,>=3.11
Requires-Dist: censys-platform<0.13.0,>=0.12.1
Requires-Dist: cryptography==46.0.3
Requires-Dist: datetime<5,>=4.3
Requires-Dist: hhhash<0.4,>=0.3
Requires-Dist: mmh3<4,>=3.0.0
Requires-Dist: pydantic==2.12.5
Requires-Dist: urllib3==2.6.3
